pycomgrader/__init__.py
pycomgrader/cli_grader.py
pycomgrader/pycomgrader.py
pycomgrader-1.2.0.dist-info/LICENSE
pycomgrader-1.2.0.dist-info/METADATA
pycomgrader-1.2.0.dist-info/WHEEL
pycomgrader-1.2.0.dist-info/entry_points.txt
pycomgrader-1.2.0.dist-info/top_level.txt
pycomgrader-1.2.0.dist-info/RECORD
