Metadata-Version: 2.2
Name: pycomgrader
Version: 1.2.0
Summary: This module provides a grader for c++ programs.
Author: Anibal Hernández
License: MIT License
Project-URL: Homepage, https://github.com/ajhglez99/PyComGrader
Keywords: competitive programming,educational,grader,c++
Classifier: License :: OSI Approved :: MIT License
Classifier: Programming Language :: Python
Classifier: Programming Language :: Python :: 3
Requires-Python: >=3.10
License-File: LICENSE
Requires-Dist: psutil
Requires-Dist: rich
